pipsqlitedbmodsV1/__init__.py
pipsqlitedbmodsV1-1.1.0.dist-info/METADATA
pipsqlitedbmodsV1-1.1.0.dist-info/WHEEL
pipsqlitedbmodsV1-1.1.0.dist-info/top_level.txt
pipsqlitedbmodsV1-1.1.0.dist-info/RECORD
