Metadata-Version: 2.1
Name: pipsqlitedbmodsV1
Version: 1.1.0
Summary: Usefull tweak package
Home-page: UNKNOWN
Author: Justus S
Author-email: justus.serim@gmail.com
License: UNKNOWN
Keywords: python
Platform: UNKNOWN
Classifier: Operating System :: Microsoft :: Windows
